vease_modeling_back/__init__.py
vease_modeling_back/app.py
vease_modeling_back/py.typed
vease_modeling_back/routes/blueprint_create.py
vease_modeling_back/routes/schemas/__init__.py
vease_modeling_back/routes/schemas/aoi.json
vease_modeling_back/routes/schemas/aoi.py
vease_modeling_back/routes/schemas/voi.json
vease_modeling_back/routes/schemas/voi.py
vease_modeling_back-1.0.0.dist-info/METADATA
vease_modeling_back-1.0.0.dist-info/WHEEL
vease_modeling_back-1.0.0.dist-info/entry_points.txt
vease_modeling_back-1.0.0.dist-info/top_level.txt
vease_modeling_back-1.0.0.dist-info/RECORD
