Metadata-Version: 2.4
Name: vease_modeling_back
Version: 1.0.0
Summary: Vease Modeling Backend - Extension for OpenGeode-Web Modeling Microservice
Author-email: Geode-solutions <team-web@geode-solutions.com>
Project-URL: Homepage, https://github.com/Geode-solutions/Vease-Modeling-Back
Project-URL: Bug Tracker, https://github.com/Geode-solutions/Vease-Modeling-Back/issues
Classifier: Programming Language :: Python :: 3
Classifier: License :: OSI Approved :: MIT License
Classifier: Operating System :: OS Independent
Requires-Python: >=3.9
Requires-Dist: opengeodeweb-back==5.*,>=5.15.0
